[
  {
    "title": "PointNet",
    "date": "2023-04-02",
    "field": "3D Object detection",
    "writer": "kiwan",
    "rawurl": "./papers/pointNet.pdf",
    "preurl": "./ppts/example.pdf"
  },
  {
    "title": "ImageNet",
    "date": "2023-04-02",
    "field": "Computer Vision",
    "writer": "Minchang",
    "rawurl": "./papers/566_imagenet_trained_cnns_are_bias.pdf",
    "preurl": "./ppts/DPRG_ImageNet_Trained_CNNs_Are_Bias.pdf"
  },
  {
    "title": "Attention Is All You Need",
    "date": "2023-04-02",
    "field": "NLP",
    "writer": "Sanghyun",
    "rawurl": "./papers/Attention Is All You Need.pdf",
    "preurl": "./ppts/example.pdf"
  },
  {
    "title": "Object Detection in 20 Years_A Survey",
    "date": "2023-04-02",
    "field": "Object detection",
    "writer": "Yoonsung",
    "rawurl": "./papers/Object Detection in 20 Years_A Survey.pdf",
    "preurl": "./ppts/example.pdf"
  },
  {
    "title":"",
    "date": "",
    "field":"",
    "writer":"",
    "rawurl":"",
    "preurl":""
  }
]
